bifas/utils/cryptography/ecdsa.py
bifas/utils/cryptography/hash.py
bifas/utils/cryptography/rsa.py
bifas/utils/cryptography/test_hash.py
bifas/utils/data_structure/binary.py
bifas/utils/data_structure/date_time.py
bifas/utils/data_structure/test_binary.py
bifas-0.1.0.dist-info/LICENSE
bifas-0.1.0.dist-info/METADATA
bifas-0.1.0.dist-info/WHEEL
bifas-0.1.0.dist-info/top_level.txt
bifas-0.1.0.dist-info/RECORD
