Metadata-Version: 2.1
Name: bifas
Version: 0.1.0
Summary: Secure ledger system, near real-time payment processing time and market deterministic transaction fee all in BIFAS.
Author-email: Mike Cheng <jaaseoi@gmail.com>
Project-URL: Homepage, https://github.com/jaaseoi/bifas
Project-URL: Bug Tracker, https://github.com/jaaseoi/bifas/issues
Classifier: Programming Language :: Python :: 3
Classifier: License :: OSI Approved :: MIT License
Classifier: Operating System :: OS Independent
Requires-Python: >=3.9
License-File: LICENSE
